odoo/addons/pos_stock_picking_invoice_link/README.rst
odoo/addons/pos_stock_picking_invoice_link/__init__.py
odoo/addons/pos_stock_picking_invoice_link/__manifest__.py
odoo/addons/pos_stock_picking_invoice_link/i18n/es.po
odoo/addons/pos_stock_picking_invoice_link/i18n/it.po
odoo/addons/pos_stock_picking_invoice_link/i18n/pos_stock_picking_invoice_link.pot
odoo/addons/pos_stock_picking_invoice_link/models/__init__.py
odoo/addons/pos_stock_picking_invoice_link/models/pos_order.py
odoo/addons/pos_stock_picking_invoice_link/models/stock_move.py
odoo/addons/pos_stock_picking_invoice_link/readme/CONTRIBUTORS.rst
odoo/addons/pos_stock_picking_invoice_link/readme/DESCRIPTION.rst
odoo/addons/pos_stock_picking_invoice_link/readme/USAGE.rst
odoo/addons/pos_stock_picking_invoice_link/static/description/icon.png
odoo/addons/pos_stock_picking_invoice_link/static/description/index.html
odoo/addons/pos_stock_picking_invoice_link/tests/__init__.py
odoo/addons/pos_stock_picking_invoice_link/tests/test_point_of_sale_stock_invoice_link.py
odoo13_addon_pos_stock_picking_invoice_link-13.0.1.0.1.dev6.dist-info/METADATA
odoo13_addon_pos_stock_picking_invoice_link-13.0.1.0.1.dev6.dist-info/WHEEL
odoo13_addon_pos_stock_picking_invoice_link-13.0.1.0.1.dev6.dist-info/top_level.txt
odoo13_addon_pos_stock_picking_invoice_link-13.0.1.0.1.dev6.dist-info/RECORD
