Metadata-Version: 2.1
Name: odoo13-addon-pos-stock-picking-invoice-link
Version: 13.0.1.0.1.dev6
Summary: POS Stock Picking Invoice Link
Home-page: https://github.com/OCA/pos
Author: Tecnativa,Odoo Community Association (OCA)
Author-email: support@odoo-community.org
License: AGPL-3
Platform: UNKNOWN
Classifier: Programming Language :: Python
Classifier: Framework :: Odoo
Classifier: Framework :: Odoo :: 13.0
Classifier: License :: OSI Approved :: GNU Affero General Public License v3
Requires-Python: >=3.5
Requires-Dist: odoo13-addon-stock-picking-invoice-link
Requires-Dist: odoo <13.1dev,>=13.0a
